LICENSE
MANIFEST.in
distribute_setup.py
setup.py
docs/Makefile
yopypi/__init__.py
yopypi/cli.py
yopypi/server.py
yopypi/status.py
yopypi.egg-info/PKG-INFO
yopypi.egg-info/SOURCES.txt
yopypi.egg-info/dependency_links.txt
yopypi.egg-info/entry_points.txt
yopypi.egg-info/requires.txt
yopypi.egg-info/top_level.txt