Metadata-Version: 1.0
Name: yopypi
Version: 0.0.2
Summary: An outgoing balancer for PYPI
Home-page: http://code.google.com/p/yopypi
Author: Alfredo Deza
Author-email: alfredodeza [at] gmail [dot] com
License: MIT
Keywords: pypi mirror performance balancer
Platform: UNKNOWN
